miptools/__init__.py
miptools-0.0.4.dist-info/METADATA
miptools-0.0.4.dist-info/WHEEL
miptools-0.0.4.dist-info/top_level.txt
miptools-0.0.4.dist-info/RECORD
